Workbook

Sheet CoverPage
B2: Tesla, Inc. — Global EV Market Sizing
B3: TAM · SAM · SOM Analysis | 2024–2030
C5: Prepared by:Aishwarya Ranjan Srivastava
B6: Date:
B7: Data Sources: IEA · OICA · Tesla 10-K · EV-Volumes ·Statista
B9: Scope: This model sizes the global BEV market using a bottom-up approach. TAM = Total global passenger car sales. SAM = BEV segments in Tesla's operating geographies. SOM = Tesla's realistic capture based on capacity and market share.

Sheet Assumptions
A1: # | B1: Variable | C1: Value | D1: Unit | E1: Source | F1: Notes
B2: SECTION 1 — Global Auto Market
A3: 3 | B3: Global passenger cars sold | C3: 73500000 | D3: Units/year | E3: OICA 2024 preliminary
A4: 4 | B4: Avg. car selling price (global) | C4: 36000 | D4: USD/unit | E4: Statista
A5: 5 | B5: Total global car market value | C5: =C3*C4 -> 2646000000000 | D5: USD | E5: calculations
B6: SECTION 2 — EV Adoption
A7: 7 | B7: Global EV sales (2024) | C7: 11000000 | D7: Units / year | E7: EA Data Explorer 2025
A8: 8 | B8: Global EV market share (2024) | C8: 0.22 | D8: % of total cars | E8: EA Data Explorer 2025 | F8: stored as decimal
A9: 9 | B9: Avg. EV selling price (global) | C9: 43000 | D9: USD / unit | E9: IEA / EV-Volumes 2024
B10: SECTION 3-Tesla Specifics
A11: 11 | B11: Tesla vehicles delivered (2024) | C11: 1789226 | D11: Units / year | E11: Tesla 2024 Annual Report
A12: 12 | B12: Tesla avg. selling price (2024) | C12: 42000 | D12: USD / unit | E12: Tesla 2024 10-K (Revenue ÷ Units)
A13: 13 | B13: Tesla revenue (2024) | C13: 97690000000 | D13: USD $ | E13: Tesla 2024 Annual Report
B14: SECTION 4-Geography Filter(for Sam)
A15: 15 | B15: Tesla operating markets (% of global EV) | C15: 0.72 | D15: % of global EV mkt | E15: IEA by country + Tesla 10-K
A16: 16 | B16: Premium EV segment share of SAM | C16: 0.35 | D16: % of SAM | E16: EV-Volumes / Statista | F16: Tesla's strongest market
A17: 17 | B17: BEV sales — North America | C17: 1300000 | D17: Units / year | E17: IEA Data Explorer 2025
A18: 18 | B18: BEV sales — Europe | C18: 2200000 | D18: Units / year | E18: IEA Data Explorer 2025
A19: 19 | B19: BEV sales — China | C19: 6400000 | D19: Units / year | E19: IEA Data Explorer 2025
A20: 20 | B20: Tesla SAM (N.America + Europe) | C20: =C17+C18 -> 3500000 | D20: Units / year | E20: IEA Data Explorer 2025
A21: 21 | B21: Tesla SAM incl. China | C21: =C17+C18+C19 -> 9900000 | D21: Units / year | E21: IEA Data Explorer 2025
A22: 22 | B22: Tesla share of core sam | C22: =C11/C20 -> 0.51120743 | D22: % of core sam | E22: calculations
A23: 23 | B23: tesla share of full sam | C23: =C11/C21 -> 0.1807299 | D23: % of full sam | E23: calculations

Sheet TAM
B1: TAM — Total Addressable Market
B2: Base Year: 2024 · Source: OICA, IEA, Statista
A3: # | B3: Metric | C3: Value | D3: Unit | E3: Formula
B4: Totals cars sold globally | C4: =Assumptions!C3 -> 73500000 | D4: Units/year | E4: Pulled from Assumptions
B5: Avg. car price (global) | C5: =Assumptions!C4 -> 36000 | D5: USD/unit | E5: Pulled from Assumptions
B6: TAM-Units | C6: =C4 -> 73500000 | D6: Units/year | E6: total cars sold
B7: TAM-Values($) | C7: =C4*C5 -> 2646000000000 | D7: USD | E7: Units × Avg price
B8: TAM by Region (2024)
B9: Global car market value | C9: =C7 -> 2646000000000
B10: — of which: EV market | C10: =Assumptions!C7*Assumptions!C9 -> 473000000000
B11: — of which: Premium EV | C11: =C10*Assumptions!C16 -> 165550000000
B12: — of which: Tesla core markets | C12: =Assumptions!C20*Assumptions!C9 -> 150500000000
B13: TAM Funnel
B14: Total global car market | C14: =C7 -> 2646000000000
B15: EV market | C15: =C10 -> 473000000000
B16: Premium EV Market | C16: =C11 -> 165550000000
B17: Tesla core market | C17: =C12 -> 150500000000

Sheet SAM_SOM
B1: SAM & SOM — Serviceable & Obtainable Market
B2: Base Year: 2024 · Source: IEA, Tesla 10-K
A3: # | B3: Metric | C3: Value | D3: Unit | E3: Formula logic
B4: SAM — Serviceable Addressable Market
A5: 5 | B5: BEV sales — N. America | C5: =Assumptions!C17 -> 1300000 | D5: Units/year | E5: Pulled from Assumptions
A6: 6 | B6: BEV sales — Europe | C6: =Assumptions!C18 -> 2200000 | D6: Units/year | E6: Pulled from Assumptions
A7: 7 | B7: BEV sales — China | C7: =Assumptions!C19 -> 6400000 | D7: Units/year | E7: Pulled from Assumptions
A8: 8 | B8: SAM — Core (ex-China) | C8: =C6+C5 -> 3500000 | D8: Units/year | E8: N.Am + Europe only
A9: 9 | B9: SAM — Full (incl. China) | C9: =C7+C8 -> 9900000 | D9: Units/year | E9: All Tesla markets
A10: 10 | B10: Avg EV price (premium) | C10: =Assumptions!C9 -> 43000 | D10: USD/unit | E10: 43000
A11: 11 | B11: SAM — Core Value ($) | C11: =C8*C10 -> 150500000000 | D11: USD | E11: Units × price
A12: 12 | B12: SAM — Full Value ($) | C12: =C10*C9 -> 425700000000 | D12: USD | E12: Units × price
B13: SOM — Serviceable Obtainable Market
A14: 14 | B14: Tesla deliveries (2024) | C14: =Assumptions!C11 -> 1789226 | D14: Units/year | E14: Actual
A15: 15 | B15: Tesla avg selling price | C15: =Assumptions!C12 -> 42000 | D15: USD/unit | E15: 42000
A16: 16 | B16: Tesla share of core SAM | C16: =Assumptions!C22 -> 0.51120743 | D16: % | E16: ~51%
A17: 17 | B17: Tesla share of full SAM | C17: =Assumptions!C23 -> 0.1807299 | D17: % | E17: ~18%
A18: 18 | B18: SOM — Units (actual) | C18: =C14 -> 1789226 | D18: Units/year | E18: Real deliveries
A19: 19 | B19: SOM-Value($) | C19: =C14*C15 -> 75147492000 | D19: USD | E19: Deliveries × ASP
B20: Market Sizing Funnel — Tesla 2024
A21: 20 | B21: TAM — Global car market | C21: =TAM!C9 -> 2646000000000 | D21: USD | E21: Calculated
A22: 21 | B22: SAM — Core BEV markets | C22: =C11 -> 150500000000 | D22: USD | E22: Calculated
A23: 22 | B23: SAM — Full BEV markets | C23: =C12 -> 425700000000 | D23: USD | E23: Calculated
A24: 23 | B24: SOM — Tesla actual revenue | C24: =C19 -> 75147492000 | D24: USD | E24: Calculated
B25: Conversion Ratios
A26: 26 | B26: TAM to core SAM | C26: =C22/C21 -> 0.056878307 | D26: % | E26: core SAM/TAM
A27: 27 | B27: TAM to Full SAM | C27: =C23/C21 -> 0.16088435 | D27: % | E27: Full SAM/TAM
A28: 28 | B28: TAM To SOM | C28: =C24/C21 -> 0.028400413 | D28: % | E28: SOM/TAM

Sheet PROJECTIONS
B1: Market Size Projections: 2024–2030
B2: Scenarios: Bear / Base / Bull · Source: IEA, Tesla 10-K
B3: Scenario Growth Rates
A4: # | B4: Metrics | C4: Bear | D4: Base | E4: Bull | F4: Unit
B5: Global BEV market growth | C5: 0.15 | D5: 0.2 | E5: 0.28 | F5: % per year
B6: Tesla market share change | C6: -0.05 | D6: 0 | E6: 0.02 | F6: % per year
B7: Avg selling price change | C7: -0.02 | D7: 0.01 | E7: 0.03 | F7: % per year
B9: TAM Projection (Global BEV Market in Units)
B10: Scenario | C10: 2024 | D10: 2025 | E10: 2026 | F10: 2027 | G10: 2028 | H10: 2029 | I10: 2030
B11: Bear | C11: =SAM_SOM!C9 -> 9900000 | D11: =C11*(1+$C$5) -> 11385000 | E11: =D11*(1+$C$5) -> 13092750 | F11: =E11*(1+$C$5) -> 15056662 | G11: =F11*(1+$C$5) -> 17315162 | H11: =G11*(1+$C$5) -> 19912436 | I11: =H11*(1+$C$5) -> 22899302
B12: Base | C12: =SAM_SOM!C9 -> 9900000 | D12: =C12*(1+$D$5) -> 11880000 | E12: =D12*(1+$D$5) -> 14256000 | F12: =E12*(1+$D$5) -> 17107200 | G12: =F12*(1+$D$5) -> 20528640 | H12: =G12*(1+$D$5) -> 24634368 | I12: =H12*(1+$D$5) -> 29561242
B13: Bull | C13: =SAM_SOM!C9 -> 9900000 | D13: =C13*(1+$E$5) -> 12672000 | E13: =D13*(1+$E$5) -> 16220160 | F13: =E13*(1+$E$5) -> 20761805 | G13: =F13*(1+$E$5) -> 26575110 | H13: =G13*(1+$E$5) -> 34016141 | I13: =H13*(1+$E$5) -> 43540660
B14: Tesla Deliveries Projection
B15: Scenario | C15: 2024 | D15: 2025 | E15: 2026 | F15: 2027 | G15: 2028 | H15: 2029 | I15: 2030
B16: Bear | C16: =SAM_SOM!C14 -> 1789226 | D16: =C16*(1+$C$6+$C$5) -> 1968148.6 | E16: =D16*(1+$C$6+$C$5) -> 2164963.5 | F16: =E16*(1+$C$6+$C$5) -> 2381459.8 | G16: =F16*(1+$C$6+$C$5) -> 2619605.8 | H16: =G16*(1+$C$6+$C$5) -> 2881566.4 | I16: =H16*(1+$C$6+$C$5) -> 3169723
B17: Base | C17: =SAM_SOM!C14 -> 1789226 | D17: =C17*(1+$D$6+$D$5) -> 2147071.2 | E17: =D17*(1+$D$6+$D$5) -> 2576485.4 | F17: =E17*(1+$D$6+$D$5) -> 3091782.5 | G17: =F17*(1+$D$6+$D$5) -> 3710139 | H17: =G17*(1+$D$6+$D$5) -> 4452166.8 | I17: =H17*(1+$D$6+$D$5) -> 5342600.2
B18: Bull | C18: =SAM_SOM!C14 -> 1789226 | D18: =C18*(1+$E$6+$E$5) -> 2325993.8 | E18: =D18*(1+$E$6+$E$5) -> 3023791.9 | F18: =E18*(1+$E$6+$E$5) -> 3930929.5 | G18: =F18*(1+$E$6+$E$5) -> 5110208.4 | H18: =G18*(1+$E$6+$E$5) -> 6643270.9 | I18: =H18*(1+$E$6+$E$5) -> 8636252.2
B19: Tesla Revenue Projection
B20: Scenario | C20: 2024 | D20: 2025 | E20: 2026 | F20: 2027 | G20: 2028 | H20: 2029 | I20: 2030
B21: Bear | C21: =SAM_SOM!C19 -> 75147492000 | D21: =C23*(1+$C$6+$C$5)*(1+$C$7) -> 8.1008996e+10 | E21: =D21*(1+$C$6+$C$5)*(1+$C$7) -> 8.7327698e+10 | F21: =E21*(1+$C$6+$C$5)*(1+$C$7) -> 9.4139259e+10 | G21: =F21*(1+$C$6+$C$5)*(1+$C$7) -> 1.0148212e+11 | H21: =G21*(1+$C$6+$C$5)*(1+$C$7) -> 1.0939773e+11 | I21: =H21*(1+$C$6+$C$5)*(1+$C$7) -> 1.1793075e+11
B22: Base | C22: =SAM_SOM!C19 -> 75147492000 | D22: =C22*(1+$D$6+$D$5)*(1+$D$7) -> 91078760304 | E22: =D22*(1+$D$6+$D$5)*(1+$D$7) -> 1.1038746e+11 | F22: =E22*(1+$D$6+$D$5)*(1+$D$7) -> 1.337896e+11 | G22: =F22*(1+$D$6+$D$5)*(1+$D$7) -> 1.6215299e+11 | H22: =G22*(1+$D$6+$D$5)*(1+$D$7) -> 1.9652943e+11 | I22: =H22*(1+$D$6+$D$5)*(1+$D$7) -> 2.3819367e+11
B23: Bull | C23: =SAM_SOM!C19 -> 75147492000 | D23: =C23*(1+$E$6+$E$5)*(1+$E$7) -> 100622491788 | E23: =D23*(1+$E$6+$E$5)*(1+$E$7) -> 1.3473352e+11 | F23: =E23*(1+$E$6+$E$5)*(1+$E$7) -> 1.8040818e+11 | G23: =F23*(1+$E$6+$E$5)*(1+$E$7) -> 2.4156655e+11 | H23: =G23*(1+$E$6+$E$5)*(1+$E$7) -> 3.2345761e+11 | I23: =H23*(1+$E$6+$E$5)*(1+$E$7) -> 4.3310974e+11
B24: 2030 Forecast Summary
B25: Scenario | C25: Bear | D25: Base | E25: Bull
B26: Global BEV market (units) | C26: =I11 -> 22899302 | D26: =I12 -> 29561242 | E26: =I13 -> 43540660
B27: Tesla deliveries | C27: =I16 -> 3169723 | D27: =I17 -> 5342600.2 | E27: =I18 -> 8636252.2
B28: Tesla revenue | C28: =I21 -> 1.1793075e+11 | D28: =I22 -> 2.3819367e+11 | E28: =I23 -> 4.3310974e+11
B29: Tesla market share | C29: =C27/C26 -> 0.13842007 | D29: =D27/D26 -> 0.1807299 | E29: =E27/E26 -> 0.19834913
